XModLb.py
XModLb-0.0.1.dist-info/LICENSE
XModLb-0.0.1.dist-info/METADATA
XModLb-0.0.1.dist-info/WHEEL
XModLb-0.0.1.dist-info/top_level.txt
XModLb-0.0.1.dist-info/RECORD
